marijbo/__init__.py
marijbo-0.0.13.dist-info/LICENSE.txt
marijbo-0.0.13.dist-info/METADATA
marijbo-0.0.13.dist-info/WHEEL
marijbo-0.0.13.dist-info/top_level.txt
marijbo-0.0.13.dist-info/RECORD
